lime_uow/__init__.py
lime_uow/exceptions.py
lime_uow/py.typed
lime_uow/pyodbc_resources/__init__.py
lime_uow/pyodbc_resources/pyodbc_connection.py
lime_uow/pyodbc_resources/pyodbc_cursor.py
lime_uow/resource.py
lime_uow/resources/__init__.py
lime_uow/resources/dummy_repository.py
lime_uow/resources/repository.py
lime_uow/resources/temp_file.py
lime_uow/shared_resource_manager.py
lime_uow/sqlalchemy_resources/__init__.py
lime_uow/sqlalchemy_resources/sqlalchemy_engine.py
lime_uow/sqlalchemy_resources/sqlalchemy_repository.py
lime_uow/sqlalchemy_resources/sqlalchemy_session.py
lime_uow/sqlalchemy_resources/sqlalchemy_transaction.py
lime_uow/unit_of_work.py
lime_uow-0.1.46.dist-info/WHEEL
lime_uow-0.1.46.dist-info/METADATA
lime_uow-0.1.46.dist-info/RECORD
