Metadata-Version: 2.1
Name: lime-uow
Version: 0.1.46
Summary: Framework to support the Unit-of-Work pattern
Home-page: https://github.com/MarkStefanovic/lime-uow
License: MIT
Author: Mark Stefanovic
Author-email: markstefanovic@hotmail.com
Requires-Python: >=3.8,<4.0
Classifier: License :: OSI Approved :: MIT License
Classifier: Programming Language :: Python :: 3
Classifier: Programming Language :: Python :: 3.8
Classifier: Programming Language :: Python :: 3.9
Provides-Extra: pyodbc
Provides-Extra: sqlalchemy
Requires-Dist: SQLAlchemy (>=1.3.19,<2.0); extra == "sqlalchemy"
Requires-Dist: pyodbc (>=4.0.30,<5.0); extra == "pyodbc"
Project-URL: Repository, https://github.com/MarkStefanovic/lime-uow
